pytan/__init__.py
pytan/_base.py
pytan/_clg.py
pytan/_discrete.py
pytan/_utils.py
pytan-0.1.0.dist-info/LICENSE
pytan-0.1.0.dist-info/METADATA
pytan-0.1.0.dist-info/WHEEL
pytan-0.1.0.dist-info/top_level.txt
pytan-0.1.0.dist-info/RECORD
